reflex_dynoselect/__init__.py
reflex_dynoselect/dynoselect.py
reflex_dynoselect/utils.py
reflex_dynoselect/options/__init__.py
reflex_dynoselect-0.1.0.dist-info/LICENSE
reflex_dynoselect-0.1.0.dist-info/METADATA
reflex_dynoselect-0.1.0.dist-info/WHEEL
reflex_dynoselect-0.1.0.dist-info/top_level.txt
reflex_dynoselect-0.1.0.dist-info/RECORD
