Metadata-Version: 2.1
Name: reflex-dynoselect
Version: 0.1.0
Summary: Generic and specialized Reflex select components. Users can search for options and create new ones. Includes specialized time zone and language select components in over 100 languages.
Author-email: Marcus Wörner <woernerm@protonmail.com>
License: Apache-2.0
Keywords: reflex,reflex-custom-components,select,timezone,time zone,locale,language,language select
Classifier: Development Status :: 4 - Beta
Requires-Python: >=3.8
License-File: LICENSE
Requires-Dist: reflex >=0.4.6
Provides-Extra: dev
Requires-Dist: build ; extra == 'dev'
Requires-Dist: twine ; extra == 'dev'
